{
  "project_info": {
    "project_number": "909016480682",
    "project_id": "vipassignment-46b8f",
    "storage_bucket": "vipassignment-46b8f.appspot.com"
  },
  "client": [
    {
      "client_info": {
        "mobilesdk_app_id": "1:909016480682:android:dae6ce146a12ac97f909d3",
        "android_client_info": {
          "package_name": "com.example.vipassignment"
        }
      },
      "oauth_client": [],
      "api_key": [
        {
          "current_key": "AIzaSyBOlJOZELcUg39pwy1v_BJS-C5htYKndgQ"
        }
      ],
      "services": {
        "appinvite_service": {
          "other_platform_oauth_client": []
        }
      }
    }
  ],
  "configuration_version": "1"
}